<?xml version="1.0" encoding="utf-8"?>
<Result Code="OK" ErrorMessage="" FullError="">
		<GlobalVars AnalysisMode="AnalyseAllBackLinks" ChargedAnalysisResUnits="5000" ChargedRetrievalResUnits="250" IndexBuildDate="2014-04-16 10:01:34" IndexType="0" RemainingAnalysisResUnits="96336727" RemainingDetailedReportsPerPeriod="950" RemainingRetrievalResUnits="19865511" RemainingStandardReports="950" ServerBuild="2014-04-16 03:14:48" ServerName="SHADOJAGUAR" ServerVersion="1.0.5219.4044" UniqueIndexID="20140416100134-HISTORICAL"/>
	<DataTables Count="2">
		<DataTable Name="RootDomain" RowsCount="250" Headers="SourceURL|ACRank|AnchorText|Date|FlagRedirect|FlagFrame|FlagNoFollow|FlagImages|FlagDeleted|FlagAltText|FlagMention|TargetURL|DomainID|FirstIndexedDate|LastSeenDate|DateLost|ReasonLost|LinkType|LinkSubType|TargetCitationFlow|TargetTrustFlow|SourceCitationFlow|SourceTrustFlow" AvailableLines="50000" BackLinkItem="frontdoor.com" BackLinkType="RootDomain" TotalBackLinks="96521646" TotalLines="50000" TotalMatches="250">
			<Row>http://www.food.com/|10|frontdoor.com|2014-03-20|0|0|0|0|0|0|0|http://www.frontdoor.com/|0|2010-11-07|2014-03-20| | |TextLink|TextLink_Normal|67|62|65|71</Row>
			<Row>http://www.hgtv.com/|10|frontdoor.com|2014-03-20|0|0|0|0|0|0|0|http://www.frontdoor.com/|1|2008-09-18|2014-03-20| | |TextLink|TextLink_Normal|67|62|66|68</Row>
			<Row>http://www.hgtv.com/|10|hgtv&#39;s frontdoor|2014-03-20|0|0|0|0|0|0|0|http://www.frontdoor.com/|1|2008-09-18|2014-03-20| | |TextLink|TextLink_Normal|67|62|66|68</Row>
			<Row>http://www.hgtv.com/|10|frontdoor|2014-03-20|0|0|0|0|0|0|0|http://www.frontdoor.com/?xp=hgtv_footer|1|2010-12-07|2014-03-20| | |TextLink|TextLink_Normal|55|53|66|68</Row>
			<Row>http://www.hgtv.com/|10|celebrity homes|2014-03-20|0|0|0|0|0|0|0|http://www.frontdoor.com/photos/celebrity-homes-an-inside-look|1|2014-03-03|2014-03-20| | |TextLink|TextLink_Normal|54|53|66|68</Row>
			<Row>http://www.hgtv.com/|10|curb appeal tricks|2014-03-20|0|0|0|0|0|0|0|http://www.frontdoor.com/curb-appeal?xp=spring|1|2014-03-17|2014-03-20| | |TextLink|TextLink_Normal|53|53|66|68</Row>
			<Row>http://www.hgtv.com/|10|outdoor living spaces of the stars|2014-03-20|0|0|0|0|0|0|0|http://www.frontdoor.com/photos/outdoor-living-spaces-of-the-stars?xp=spring|1|2014-03-17|2014-03-20| | |TextLink|TextLink_Normal|53|53|66|68</Row>
			<Row>http://www.hgtv.com/|10|10 homes with incredible decks|2014-03-20|0|0|0|0|0|0|0|http://www.frontdoor.com/photos/10-homes-for-sale-with-amazing-decks?xp=spring|1|2014-03-17|2014-03-20| | |TextLink|TextLink_Normal|53|53|66|68</Row>
			<Row>http://www.diynetwork.com/|10|frontdoor.com|2014-03-20|0|0|0|0|0|0|0|http://www.frontdoor.com/|2|2008-09-18|2014-03-20| | |TextLink|TextLink_Normal|67|62|65|66</Row>
			<Row>http://www.diynetwork.com/|10|hgtv&#39;s frontdoor|2014-03-20|0|0|0|0|0|0|0|http://www.frontdoor.com/|2|2008-09-18|2014-03-20| | |TextLink|TextLink_Normal|67|62|65|66</Row>
			<Row>http://www.diynetwork.com/|10|frontdoor|2014-03-20|0|0|0|0|0|0|0|http://www.frontdoor.com/?xp=diy_footer|2|2011-01-06|2014-03-20| | |TextLink|TextLink_Normal|49|46|65|66</Row>
			<Row>http://www.diynetwork.com/|10|curb appeal tricks|2014-03-20|0|0|0|0|0|0|0|http://www.frontdoor.com/curb-appeal?xp=diy_footer|2|2014-03-17|2014-03-20| | |TextLink|TextLink_Normal|49|46|65|66</Row>
			<Row>http://www.diynetwork.com/|10|living spaces of the stars|2014-03-20|0|0|0|0|0|0|0|http://www.frontdoor.com/photos/outdoor-living-spaces-of-the-stars?xp=diy_footer|2|2014-03-17|2014-03-20| | |TextLink|TextLink_Normal|49|46|65|66</Row>
			<Row>http://www.diynetwork.com/|10|homes with incredible decks|2014-03-20|0|0|0|0|0|0|0|http://www.frontdoor.com/photos/10-homes-for-sale-with-amazing-decks?xp=diy_footer|2|2014-03-17|2014-03-20| | |TextLink|TextLink_Normal|49|46|65|66</Row>
			<Row>http://www.scrippsnetworksinteractive.com/privacy-policy/|10|frontdoor|2014-03-19|0|0|0|0|0|0|0|http://www.frontdoor.com/|3|2012-10-26|2014-03-19| | |TextLink|TextLink_Normal|67|62|67|64</Row>
			<Row>http://www.travelchannel.com/|10|frontdoor.com|2014-03-20|0|0|0|0|0|0|0|http://www.frontdoor.com/|4|2011-12-02|2014-03-20| | |TextLink|TextLink_Normal|67|62|65|65</Row>
			<Row>http://www.scrippsnetworksinteractive.com/terms-of-use/|10|frontdoor|2014-03-19|0|0|0|0|0|0|0|http://www.frontdoor.com/|3|2012-10-26|2014-03-19| | |TextLink|TextLink_Normal|67|62|66|63</Row>
			<Row>http://www.gactv.com/|10|frontdoor.com|2014-03-20|0|0|0|0|0|0|0|http://www.frontdoor.com/|5|2009-12-12|2014-03-20| | |TextLink|TextLink_Normal|67|62|65|63</Row>
			<Row>http://www.hgtvremodels.com/|10|frontdoor.com|2014-03-20|0|0|0|0|0|0|0|http://www.frontdoor.com/|6|2011-10-03|2014-03-20| | |TextLink|TextLink_Normal|67|62|65|62</Row>
			<Row>http://www.hgtvremodels.com/|10|hgtv&#39;s frontdoor|2014-03-20|0|0|0|0|0|0|0|http://www.frontdoor.com/|6|2011-10-03|2014-03-20| | |TextLink|TextLink_Normal|67|62|65|62</Row>
			<Row>http://www.hgtvremodels.com/|10|frontdoor|2014-03-20|0|0|0|0|0|0|0|http://www.frontdoor.com/?xp=hgrm_footer|6|2011-10-03|2014-03-20| | |TextLink|TextLink_Normal|47|41|65|62</Row>
			<Row>http://www.hgtvremodels.com/|10|curb appeal tricks|2014-03-20|0|0|0|0|0|0|0|http://www.frontdoor.com/curb-appeal?xp=hgrm_footer|6|2014-03-17|2014-03-20| | |TextLink|TextLink_Normal|47|41|65|62</Row>
			<Row>http://www.hgtvremodels.com/|10|living spaces of the stars|2014-03-20|0|0|0|0|0|0|0|http://www.frontdoor.com/photos/outdoor-living-spaces-of-the-stars?xp=hgrm_footer|6|2014-03-17|2014-03-20| | |TextLink|TextLink_Normal|47|41|65|62</Row>
			<Row>http://www.hgtvremodels.com/|10|10 homes with incredible decks|2014-03-20|0|0|0|0|0|0|0|http://www.frontdoor.com/photos/10-homes-for-sale-with-amazing-decks?xp=hgrm_footer|6|2014-03-17|2014-03-20| | |TextLink|TextLink_Normal|47|41|65|62</Row>
			<Row>http://www.travelchannel.com/sweepstakes/the-trip?xp=trip|10|frontdoor.com|2014-03-19|0|0|0|0|0|0|0|http://www.frontdoor.com/|4|2014-01-21|2014-03-19| | |TextLink|TextLink_Normal|67|62|65|61</Row>
			<Row>http://www.hgtvgardens.com/|9|hgtv&#39;s frontdoor|2014-03-20|0|0|0|0|0|0|0|http://www.frontdoor.com/|7|2013-03-26|2014-03-20| | |TextLink|TextLink_Normal|67|62|63|63</Row>
			<Row>http://www.cookingchanneltv.com/home.html|10|frontdoor.com|2014-03-20|0|0|0|0|0|0|0|http://www.frontdoor.com/|8|2013-02-24|2014-03-20| | |TextLink|TextLink_Normal|67|62|64|61</Row>
			<Row>http://www.scrippsnetworksinteractive.com/|10|frontdoor|2014-03-20|0|0|0|0|0|0|0|http://www.frontdoor.com/|3|2012-09-27|2014-03-20| | |TextLink|TextLink_Normal|67|62|64|61</Row>
			<Row>http://www.hgtv.com/property-brothers/show/index.html?xp=property|9|frontdoor.com|2014-03-19|0|0|0|0|0|0|0|http://www.frontdoor.com/|1|2013-09-21|2014-03-19| | |TextLink|TextLink_Normal|67|62|63|58</Row>
			<Row>http://www.hgtv.com/property-brothers/show/index.html?xp=property|9|hgtv&#39;s frontdoor|2014-03-19|0|0|0|0|0|0|0|http://www.frontdoor.com/|1|2013-09-21|2014-03-19| | |TextLink|TextLink_Normal|67|62|63|58</Row>
			<Row>http://www.hgtv.com/property-brothers/show/index.html?xp=property|9|frontdoor|2014-03-19|0|0|0|0|0|0|0|http://www.frontdoor.com/?xp=hgtv_footer|1|2013-09-21|2014-03-19| | |TextLink|TextLink_Normal|55|53|63|58</Row>
			<Row>http://www.hgtv.com/property-brothers/show/index.html?xp=property|9|celebrity homes|2014-03-19|0|0|0|0|0|0|0|http://www.frontdoor.com/photos/celebrity-homes-an-inside-look|1|2014-03-03|2014-03-19| | |TextLink|TextLink_Normal|54|53|63|58</Row>
			<Row>http://www.hgtv.com/property-brothers/show/index.html?xp=property|9|curb appeal tricks|2014-03-19|0|0|0|0|0|0|0|http://www.frontdoor.com/curb-appeal?xp=spring|1|2014-03-17|2014-03-19| | |TextLink|TextLink_Normal|53|53|63|58</Row>
			<Row>http://www.hgtv.com/property-brothers/show/index.html?xp=property|9|outdoor living spaces of the stars|2014-03-19|0|0|0|0|0|0|0|http://www.frontdoor.com/photos/outdoor-living-spaces-of-the-stars?xp=spring|1|2014-03-17|2014-03-19| | |TextLink|TextLink_Normal|53|53|63|58</Row>
			<Row>http://www.hgtv.com/property-brothers/show/index.html?xp=property|9|10 homes with incredible decks|2014-03-19|0|0|0|0|0|0|0|http://www.frontdoor.com/photos/10-homes-for-sale-with-amazing-decks?xp=spring|1|2014-03-17|2014-03-19| | |TextLink|TextLink_Normal|53|53|63|58</Row>
			<Row>http://www.hgtv.com/spring-season-decks-patios-outdoor-spaces/package/index.html?xp=spring|9|frontdoor.com|2014-03-18|0|0|0|0|0|0|0|http://www.frontdoor.com/|1|2014-03-18|2014-03-18| | |TextLink|TextLink_Normal|67|62|63|58</Row>
			<Row>http://www.hgtv.com/spring-season-decks-patios-outdoor-spaces/package/index.html?xp=spring|9|hgtv&#39;s frontdoor|2014-03-18|0|0|0|0|0|0|0|http://www.frontdoor.com/|1|2014-03-18|2014-03-18| | |TextLink|TextLink_Normal|67|62|63|58</Row>
			<Row>http://www.hgtv.com/spring-season-decks-patios-outdoor-spaces/package/index.html?xp=spring|9|frontdoor|2014-03-18|0|0|0|0|0|0|0|http://www.frontdoor.com/?xp=hgtv_footer|1|2014-03-18|2014-03-18| | |TextLink|TextLink_Normal|55|53|63|58</Row>
			<Row>http://www.hgtv.com/spring-season-decks-patios-outdoor-spaces/package/index.html?xp=spring|9|celebrity homes|2014-03-18|0|0|0|0|0|0|0|http://www.frontdoor.com/photos/celebrity-homes-an-inside-look|1|2014-03-18|2014-03-18| | |TextLink|TextLink_Normal|54|53|63|58</Row>
			<Row>http://www.hgtv.com/spring-season-decks-patios-outdoor-spaces/package/index.html?xp=spring|9|curb appeal tricks|2014-03-18|0|0|0|0|0|0|0|http://www.frontdoor.com/curb-appeal?xp=spring|1|2014-03-18|2014-03-18| | |TextLink|TextLink_Normal|53|53|63|58</Row>
			<Row>http://www.hgtv.com/spring-season-decks-patios-outdoor-spaces/package/index.html?xp=spring|9|outdoor living spaces of the stars|2014-03-18|0|0|0|0|0|0|0|http://www.frontdoor.com/photos/outdoor-living-spaces-of-the-stars?xp=spring|1|2014-03-18|2014-03-18| | |TextLink|TextLink_Normal|53|53|63|58</Row>
			<Row>http://www.hgtv.com/spring-season-decks-patios-outdoor-spaces/package/index.html?xp=spring|9|10 homes with incredible decks|2014-03-18|0|0|0|0|0|0|0|http://www.frontdoor.com/photos/10-homes-for-sale-with-amazing-decks?xp=spring|1|2014-03-18|2014-03-18| | |TextLink|TextLink_Normal|53|53|63|58</Row>
			<Row>http://www.hgtv.com/spring-season-decks-patios-outdoor-spaces/package/index.html?xp=spring|9|21 opulent outdoor rooms|2014-03-18|0|0|0|0|0|0|0|http://www.frontdoor.com/photos/21-opulent-outdoor-rooms|1|2014-03-18|2014-03-18| | |TextLink|TextLink_Normal|36|34|63|58</Row>
			<Row>http://www.hgtv.com/spring-season-decks-patios-outdoor-spaces/package/index.html?xp=spring|9|outdoor deck|2014-03-18|0|0|0|1|0|0|0|http://www.frontdoor.com/photos/dramatic-decks-and-patios|1|2014-03-18|2014-03-18| | |ImageLink|ImageLink_Normal|36|34|63|58</Row>
			<Row>http://www.hgtv.com/spring-season-decks-patios-outdoor-spaces/package/index.html?xp=spring|9|dramatic decks and patios|2014-03-18|0|0|0|0|0|0|0|http://www.frontdoor.com/photos/dramatic-decks-and-patios|1|2014-03-18|2014-03-18| | |TextLink|TextLink_Normal|36|34|63|58</Row>
			<Row>http://www.hgtv.com/spring-season-decks-patios-outdoor-spaces/package/index.html?xp=spring|9|over-the-top backyards|2014-03-18|0|0|0|0|0|0|0|http://www.frontdoor.com/photos/dramatic-decks-and-patios|1|2014-03-18|2014-03-18| | |TextLink|TextLink_Normal|36|34|63|58</Row>
			<Row>http://www.hgtv.com/spring-season-decks-patios-outdoor-spaces/package/index.html?xp=spring|9|celebrity room showdown|2014-03-18|0|0|0|0|0|0|0|http://www.frontdoor.com/photos/celebrity-room-showdown-outdoor-rooms|1|2014-03-18|2014-03-18| | |TextLink|TextLink_Normal|35|34|63|58</Row>
			<Row>http://www.hgtv.com/spring-season-decks-patios-outdoor-spaces/package/index.html?xp=spring|9|urban homes with gorgeous gardens|2014-03-18|0|0|0|0|0|0|0|http://www.frontdoor.com/photos/5-manhattan-homes-with-gorgeous-gardens|1|2014-03-18|2014-03-18| | |TextLink|TextLink_Normal|35|34|63|58</Row>
			<Row>http://www.cookingchanneltv.com/site/about-us/get-cooking-fine-living-fans.html|8|frontdoor.com|2014-03-20|0|0|0|0|0|0|0|http://www.frontdoor.com/|8|2013-01-25|2014-03-20| | |TextLink|TextLink_Normal|67|62|56|60</Row>
			<Row>http://www.hgtv.com/shop/package/index.html|9|frontdoor.com|2014-03-20|0|0|0|0|0|0|0|http://www.frontdoor.com/|1|2013-07-24|2014-03-20| | |TextLink|TextLink_Normal|67|62|58|56</Row>
			<Row>http://www.hgtv.com/shop/package/index.html|9|hgtv&#39;s frontdoor|2014-03-20|0|0|0|0|0|0|0|http://www.frontdoor.com/|1|2013-07-24|2014-03-20| | |TextLink|TextLink_Normal|67|62|58|56</Row>
			<Row>http://www.hgtv.com/shop/package/index.html|9|frontdoor|2014-03-20|0|0|0|0|0|0|0|http://www.frontdoor.com/?xp=hgtv_footer|1|2013-08-23|2014-03-20| | |TextLink|TextLink_Normal|55|53|58|56</Row>
			<Row>http://www.hgtv.com/shop/package/index.html|9|celebrity homes|2014-03-20|0|0|0|0|0|0|0|http://www.frontdoor.com/photos/celebrity-homes-an-inside-look|1|2014-03-03|2014-03-20| | |TextLink|TextLink_Normal|54|53|58|56</Row>
			<Row>http://www.hgtv.com/shop/package/index.html|9|curb appeal tricks|2014-03-20|0|0|0|0|0|0|0|http://www.frontdoor.com/curb-appeal?xp=spring|1|2014-03-17|2014-03-20| | |TextLink|TextLink_Normal|53|53|58|56</Row>
			<Row>http://www.hgtv.com/shop/package/index.html|9|outdoor living spaces of the stars|2014-03-20|0|0|0|0|0|0|0|http://www.frontdoor.com/photos/outdoor-living-spaces-of-the-stars?xp=spring|1|2014-03-17|2014-03-20| | |TextLink|TextLink_Normal|53|53|58|56</Row>
			<Row>http://www.hgtv.com/shop/package/index.html|9|10 homes with incredible decks|2014-03-20|0|0|0|0|0|0|0|http://www.frontdoor.com/photos/10-homes-for-sale-with-amazing-decks?xp=spring|1|2014-03-17|2014-03-20| | |TextLink|TextLink_Normal|53|53|58|56</Row>
			<Row>http://www.food.com/menus|9|frontdoor.com|2014-03-20|0|0|0|0|0|0|0|http://www.frontdoor.com/|0|2013-05-25|2014-03-20| | |TextLink|TextLink_Normal|67|62|63|50</Row>
			<Row>http://www.scrippsnetworksdigital.com/login.aspx?auto=false&#38;pr=foodcat/default.aspx|9|frontdoor.com|2014-03-20|0|0|0|0|0|0|0|http://www.frontdoor.com/|9|2013-12-17|2014-03-20| | |TextLink|TextLink_Normal|67|62|59|54</Row>
			<Row>http://www.scrippsnetworksdigital.com/login.aspx?auto=false&#38;pr=homecat/default.aspx|9|frontdoor.com|2014-03-20|0|0|0|0|0|0|0|http://www.frontdoor.com/|9|2013-09-22|2014-03-20| | |TextLink|TextLink_Normal|67|62|57|56</Row>
			<Row>http://www.hgtvhome.com/|9|hgtv&#39;s frontdoor|2014-03-19|0|0|0|0|0|0|0|http://www.frontdoor.com/|10|2013-02-23|2014-03-19| | |TextLink|TextLink_Normal|67|62|57|56</Row>
			<Row>http://www.hgtvhome.com/|9|frontdoor.com|2014-03-19|0|0|0|0|0|0|0|http://www.frontdoor.com/|10|2013-02-23|2014-03-19| | |TextLink|TextLink_Normal|67|62|57|56</Row>
			<Row>http://www.hgtv.com/?xp=food_footer|9|frontdoor.com|2014-03-20|0|0|0|0|0|0|0|http://www.frontdoor.com/|1|2011-03-07|2014-03-20| | |TextLink|TextLink_Normal|67|62|59|53</Row>
			<Row>http://www.hgtv.com/?xp=food_footer|9|hgtv&#39;s frontdoor|2014-03-20|0|0|0|0|0|0|0|http://www.frontdoor.com/|1|2011-03-07|2014-03-20| | |TextLink|TextLink_Normal|67|62|59|53</Row>
			<Row>http://www.hgtv.com/?xp=food_footer|9|frontdoor|2014-03-20|0|0|0|0|0|0|0|http://www.frontdoor.com/?xp=hgtv_footer|1|2011-02-05|2014-03-20| | |TextLink|TextLink_Normal|55|53|59|53</Row>
			<Row>http://www.hgtv.com/?xp=food_footer|9|celebrity homes|2014-03-20|0|0|0|0|0|0|0|http://www.frontdoor.com/photos/celebrity-homes-an-inside-look|1|2014-03-03|2014-03-20| | |TextLink|TextLink_Normal|54|53|59|53</Row>
			<Row>http://www.hgtv.com/?xp=food_footer|9|curb appeal tricks|2014-03-20|0|0|0|0|0|0|0|http://www.frontdoor.com/curb-appeal?xp=spring|1|2014-03-20|2014-03-20| | |TextLink|TextLink_Normal|53|53|59|53</Row>
			<Row>http://www.hgtv.com/?xp=food_footer|9|outdoor living spaces of the stars|2014-03-20|0|0|0|0|0|0|0|http://www.frontdoor.com/photos/outdoor-living-spaces-of-the-stars?xp=spring|1|2014-03-20|2014-03-20| | |TextLink|TextLink_Normal|53|53|59|53</Row>
			<Row>http://www.hgtv.com/?xp=food_footer|9|10 homes with incredible decks|2014-03-20|0|0|0|0|0|0|0|http://www.frontdoor.com/photos/10-homes-for-sale-with-amazing-decks?xp=spring|1|2014-03-20|2014-03-20| | |TextLink|TextLink_Normal|53|53|59|53</Row>
			<Row>http://www.cookingchanneltv.com/home.html?xp=food_footer|9|frontdoor.com|2014-03-20|0|0|0|0|0|0|0|http://www.frontdoor.com/|8|2013-07-24|2014-03-20| | |TextLink|TextLink_Normal|67|62|59|53</Row>
			<Row>http://www.foodnetwork.com/site/dmca--digital-millennium-copyright-act-notice-and-policy.html|9|www.frontdoor.com|2014-03-20|0|0|0|0|0|0|0|http://www.frontdoor.com/|11|2014-01-23|2014-03-20| | |TextLink|TextLink_Normal|67|62|59|52</Row>
			<Row>http://www.food.com/slideshow/low-calorie-snack-recipes-for-busy-moms-178?xp=food_footer|9|frontdoor.com|2014-03-19|0|0|0|0|0|0|0|http://www.frontdoor.com/|0|2014-02-04|2014-03-19| | |TextLink|TextLink_Normal|67|62|59|52</Row>
			<Row>http://www.food.com/contests/simply-potatoes?xp=food_footer|9|frontdoor.com|2014-03-20|0|0|0|0|0|0|0|http://www.frontdoor.com/|0|2014-03-18|2014-03-20| | |TextLink|TextLink_Normal|67|62|59|52</Row>
			<Row>http://www.food.com/slideshow/birthday-party-recipes-for-busy-moms-204?xp=food_footer|9|frontdoor.com|2014-03-18|0|0|0|0|0|0|0|http://www.frontdoor.com/|0|2014-03-18|2014-03-18| | |TextLink|TextLink_Normal|67|62|59|52</Row>
			<Row>http://www.travelchannel.com/?xp=food_footer|9|frontdoor.com|2014-03-20|0|0|0|0|0|0|0|http://www.frontdoor.com/|4|2012-10-27|2014-03-20| | |TextLink|TextLink_Normal|67|62|59|52</Row>
			<Row>http://www.hgtv.com/landscaping/small-space-gardening-tips-for-apartment-dwellers-and-urbanites/pictures/index.html?xp=food_footer|9|hgtv&#39;s frontdoor|2014-03-18|0|0|0|0|0|0|0|http://www.frontdoor.com/|1|2014-03-18|2014-03-18| | |TextLink|TextLink_Normal|67|62|58|52</Row>
			<Row>http://www.hgtv.com/landscaping/small-space-gardening-tips-for-apartment-dwellers-and-urbanites/pictures/index.html?xp=food_footer|9|frontdoor.com|2014-03-18|0|0|0|0|0|0|0|http://www.frontdoor.com/|1|2014-03-18|2014-03-18| | |TextLink|TextLink_Normal|67|62|58|52</Row>
			<Row>http://www.hgtv.com/landscaping/small-space-gardening-tips-for-apartment-dwellers-and-urbanites/pictures/index.html?xp=food_footer|9|frontdoor|2014-03-18|0|0|0|0|0|0|0|http://www.frontdoor.com/?xp=hgtv_footer|1|2014-03-18|2014-03-18| | |TextLink|TextLink_Normal|55|53|58|52</Row>
			<Row>http://www.hgtv.com/landscaping/small-space-gardening-tips-for-apartment-dwellers-and-urbanites/pictures/index.html?xp=food_footer|9|celebrity homes|2014-03-18|0|0|0|0|0|0|0|http://www.frontdoor.com/photos/celebrity-homes-an-inside-look|1|2014-03-18|2014-03-18| | |TextLink|TextLink_Normal|54|53|58|52</Row>
			<Row>http://www.hgtv.com/landscaping/small-space-gardening-tips-for-apartment-dwellers-and-urbanites/pictures/index.html?xp=food_footer|9|curb appeal tricks|2014-03-18|0|0|0|0|0|0|0|http://www.frontdoor.com/curb-appeal?xp=spring|1|2014-03-18|2014-03-18| | |TextLink|TextLink_Normal|53|53|58|52</Row>
			<Row>http://www.hgtv.com/landscaping/small-space-gardening-tips-for-apartment-dwellers-and-urbanites/pictures/index.html?xp=food_footer|9|outdoor living spaces of the stars|2014-03-18|0|0|0|0|0|0|0|http://www.frontdoor.com/photos/outdoor-living-spaces-of-the-stars?xp=spring|1|2014-03-18|2014-03-18| | |TextLink|TextLink_Normal|53|53|58|52</Row>
			<Row>http://www.hgtv.com/landscaping/small-space-gardening-tips-for-apartment-dwellers-and-urbanites/pictures/index.html?xp=food_footer|9|10 homes with incredible decks|2014-03-18|0|0|0|0|0|0|0|http://www.frontdoor.com/photos/10-homes-for-sale-with-amazing-decks?xp=spring|1|2014-03-18|2014-03-18| | |TextLink|TextLink_Normal|53|53|58|52</Row>
			<Row>http://www.travelchannel.com/interests/travels-best/photos/travels-best-beach-awards-2014?xp=food_footer|9|frontdoor.com|2014-03-20|0|0|0|0|0|0|0|http://www.frontdoor.com/|4|2014-03-04|2014-03-20| | |TextLink|TextLink_Normal|67|62|58|52</Row>
			<Row>http://www.travelchannel.com/video/the-many-flavors-of-hawaii?xp=food_footer|9|frontdoor.com|2014-03-18|0|0|0|0|0|0|0|http://www.frontdoor.com/|4|2014-03-18|2014-03-18| | |TextLink|TextLink_Normal|67|62|58|52</Row>
			<Row>http://www.roomzaar.com/rate-my-space/multigallery.esi|8|frontdoor.com|2014-03-20|0|0|0|0|0|0|0|http://www.frontdoor.com/|12|2011-03-07|2014-03-20| | |TextLink|TextLink_Normal|67|62|56|54</Row>
			<Row>http://www.roomzaar.com/rate-my-space/multigallery.esi|8|hgtv&#39;s frontdoor|2014-03-20|0|0|0|0|0|0|0|http://www.frontdoor.com/|12|2011-03-07|2014-03-20| | |TextLink|TextLink_Normal|67|62|56|54</Row>
			<Row>http://www.roomzaar.com/rate-my-space/multigallery.esi|8|frontdoor|2014-03-20|0|0|0|0|0|0|0|http://www.frontdoor.com/?xp=hgtv_footer|12|2011-03-07|2014-03-20| | |TextLink|TextLink_Normal|55|53|56|54</Row>
			<Row>http://www.roomzaar.com/rate-my-space/multigallery.esi|8|celebrity homes|2014-03-20|0|0|0|0|0|0|0|http://www.frontdoor.com/photos/celebrity-homes-an-inside-look|12|2014-03-03|2014-03-20| | |TextLink|TextLink_Normal|54|53|56|54</Row>
			<Row>http://www.roomzaar.com/rate-my-space/multigallery.esi|8|curb appeal tricks|2014-03-20|0|0|0|0|0|0|0|http://www.frontdoor.com/curb-appeal?xp=spring|12|2014-03-17|2014-03-20| | |TextLink|TextLink_Normal|53|53|56|54</Row>
			<Row>http://www.roomzaar.com/rate-my-space/multigallery.esi|8|outdoor living spaces of the stars|2014-03-20|0|0|0|0|0|0|0|http://www.frontdoor.com/photos/outdoor-living-spaces-of-the-stars?xp=spring|12|2014-03-17|2014-03-20| | |TextLink|TextLink_Normal|53|53|56|54</Row>
			<Row>http://www.roomzaar.com/rate-my-space/multigallery.esi|8|10 homes with incredible decks|2014-03-20|0|0|0|0|0|0|0|http://www.frontdoor.com/photos/10-homes-for-sale-with-amazing-decks?xp=spring|12|2014-03-17|2014-03-20| | |TextLink|TextLink_Normal|53|53|56|54</Row>
			<Row>http://my.hgtv.com/home/home.esi|8|frontdoor.com|2014-03-20|0|0|0|0|0|0|0|http://www.frontdoor.com/|1|2011-03-07|2014-03-20| | |TextLink|TextLink_Normal|67|62|55|54</Row>
			<Row>http://my.hgtv.com/home/home.esi|8|hgtv&#39;s frontdoor|2014-03-20|0|0|0|0|0|0|0|http://www.frontdoor.com/|1|2011-03-07|2014-03-20| | |TextLink|TextLink_Normal|67|62|55|54</Row>
			<Row>http://my.hgtv.com/home/home.esi|8|frontdoor|2014-03-20|0|0|0|0|0|0|0|http://www.frontdoor.com/?xp=hgtv_footer|1|2011-04-06|2014-03-20| | |TextLink|TextLink_Normal|55|53|55|54</Row>
			<Row>http://my.hgtv.com/home/home.esi|8|celebrity homes|2014-03-20|0|0|0|0|0|0|0|http://www.frontdoor.com/photos/celebrity-homes-an-inside-look|1|2014-03-04|2014-03-20| | |TextLink|TextLink_Normal|54|53|55|54</Row>
			<Row>http://my.hgtv.com/home/home.esi|8|curb appeal tricks|2014-03-20|0|0|0|0|0|0|0|http://www.frontdoor.com/curb-appeal?xp=spring|1|2014-03-17|2014-03-20| | |TextLink|TextLink_Normal|53|53|55|54</Row>
			<Row>http://my.hgtv.com/home/home.esi|8|outdoor living spaces of the stars|2014-03-20|0|0|0|0|0|0|0|http://www.frontdoor.com/photos/outdoor-living-spaces-of-the-stars?xp=spring|1|2014-03-17|2014-03-20| | |TextLink|TextLink_Normal|53|53|55|54</Row>
			<Row>http://my.hgtv.com/home/home.esi|8|10 homes with incredible decks|2014-03-20|0|0|0|0|0|0|0|http://www.frontdoor.com/photos/10-homes-for-sale-with-amazing-decks?xp=spring|1|2014-03-17|2014-03-20| | |TextLink|TextLink_Normal|53|53|55|54</Row>
			<Row>http://www.hgtv.com/dream-home-2014-piece-of-the-dream-vote-thanks/package/index.html|8|hgtv&#39;s frontdoor|2014-03-19|0|0|0|0|0|0|0|http://www.frontdoor.com/|1|2014-01-15|2014-03-19| | |TextLink|TextLink_Normal|67|62|55|54</Row>
			<Row>http://www.hgtv.com/dream-home-2014-piece-of-the-dream-vote-thanks/package/index.html|8|frontdoor.com|2014-03-19|0|0|0|0|0|0|0|http://www.frontdoor.com/|1|2014-01-15|2014-03-19| | |TextLink|TextLink_Normal|67|62|55|54</Row>
			<Row>http://www.hgtv.com/dream-home-2014-piece-of-the-dream-vote-thanks/package/index.html|8|frontdoor|2014-03-19|0|0|0|0|0|0|0|http://www.frontdoor.com/?xp=hgtv_footer|1|2013-12-29|2014-03-19| | |TextLink|TextLink_Normal|55|53|55|54</Row>
			<Row>http://www.hgtv.com/dream-home-2014-piece-of-the-dream-vote-thanks/package/index.html|8|celebrity homes|2014-03-19|0|0|0|0|0|0|0|http://www.frontdoor.com/photos/celebrity-homes-an-inside-look|1|2014-03-03|2014-03-19| | |TextLink|TextLink_Normal|54|53|55|54</Row>
			<Row>http://www.hgtv.com/dream-home-2014-piece-of-the-dream-vote-thanks/package/index.html|8|curb appeal tricks|2014-03-19|0|0|0|0|0|0|0|http://www.frontdoor.com/curb-appeal?xp=spring|1|2014-03-17|2014-03-19| | |TextLink|TextLink_Normal|53|53|55|54</Row>
			<Row>http://www.hgtv.com/dream-home-2014-piece-of-the-dream-vote-thanks/package/index.html|8|outdoor living spaces of the stars|2014-03-19|0|0|0|0|0|0|0|http://www.frontdoor.com/photos/outdoor-living-spaces-of-the-stars?xp=spring|1|2014-03-17|2014-03-19| | |TextLink|TextLink_Normal|53|53|55|54</Row>
			<Row>http://www.hgtv.com/dream-home-2014-piece-of-the-dream-vote-thanks/package/index.html|8|10 homes with incredible decks|2014-03-19|0|0|0|0|0|0|0|http://www.frontdoor.com/photos/10-homes-for-sale-with-amazing-decks?xp=spring|1|2014-03-17|2014-03-19| | |TextLink|TextLink_Normal|53|53|55|54</Row>
			<Row>http://www.hgtv.com/dream-home-2014-piece-of-the-dream-vote-thanks/package/index.html|8|truckee, ca|2014-03-19|0|0|0|0|0|0|0|http://www.frontdoor.com/dreamhome|1|2013-12-29|2014-03-19| | |TextLink|TextLink_Normal|41|38|55|54</Row>
			<Row>http://www.hgtv.com/dream-home-2014-piece-of-the-dream-vote-thanks/package/index.html|8|lake tahoe hot spots|2014-03-19|0|0|0|0|0|0|0|http://www.frontdoor.com/photos/lake-tahoe-hot-spots-and-tourist-attractions|1|2013-12-29|2014-03-19| | |TextLink|TextLink_Normal|40|38|55|54</Row>
			<Row>http://www.hgtv.com/dream-home-2014-piece-of-the-dream-vote-thanks/package/index.html|8|around the neighborhood|2014-03-19|0|0|0|0|0|0|0|http://www.frontdoor.com/places/5-great-neighborhoods-in-the-lake-tahoe-area|1|2013-12-29|2014-03-19| | |TextLink|TextLink_Normal|39|38|55|54</Row>
			<Row>http://www.hgtv.com/dream-home-2014-piece-of-the-dream-vote-thanks/package/index.html|8|frontdoor.com|2014-03-19|0|0|0|0|0|0|0|http://www.frontdoor.com/hgtv-dream-home-2014-giveaway-entry-form|1|2014-01-17|2014-03-19| | |TextLink|TextLink_Normal|30|32|55|54</Row>
			<Row>http://www.hgtv.com/hgtv-full-episodes/videos/index.html|8|frontdoor.com|2014-03-20|0|0|0|0|0|0|0|http://www.frontdoor.com/|1|2014-02-19|2014-03-20| | |TextLink|TextLink_Normal|67|62|55|54</Row>
			<Row>http://www.hgtv.com/hgtv-full-episodes/videos/index.html|8|hgtv&#39;s frontdoor|2014-03-20|0|0|0|0|0|0|0|http://www.frontdoor.com/|1|2014-02-19|2014-03-20| | |TextLink|TextLink_Normal|67|62|55|54</Row>
			<Row>http://www.hgtv.com/hgtv-full-episodes/videos/index.html|8|frontdoor|2014-03-20|0|0|0|0|0|0|0|http://www.frontdoor.com/?xp=hgtv_footer|1|2014-02-19|2014-03-20| | |TextLink|TextLink_Normal|55|53|55|54</Row>
			<Row>http://www.hgtv.com/hgtv-full-episodes/videos/index.html|8|celebrity homes|2014-03-20|0|0|0|0|0|0|0|http://www.frontdoor.com/photos/celebrity-homes-an-inside-look|1|2014-03-03|2014-03-20| | |TextLink|TextLink_Normal|54|53|55|54</Row>
			<Row>http://www.hgtv.com/hgtv-full-episodes/videos/index.html|8|curb appeal tricks|2014-03-20|0|0|0|0|0|0|0|http://www.frontdoor.com/curb-appeal?xp=spring|1|2014-03-17|2014-03-20| | |TextLink|TextLink_Normal|53|53|55|54</Row>
			<Row>http://www.hgtv.com/hgtv-full-episodes/videos/index.html|8|outdoor living spaces of the stars|2014-03-20|0|0|0|0|0|0|0|http://www.frontdoor.com/photos/outdoor-living-spaces-of-the-stars?xp=spring|1|2014-03-17|2014-03-20| | |TextLink|TextLink_Normal|53|53|55|54</Row>
			<Row>http://www.hgtv.com/hgtv-full-episodes/videos/index.html|8|10 homes with incredible decks|2014-03-20|0|0|0|0|0|0|0|http://www.frontdoor.com/photos/10-homes-for-sale-with-amazing-decks?xp=spring|1|2014-03-17|2014-03-20| | |TextLink|TextLink_Normal|53|53|55|54</Row>
			<Row>http://blog.hgtv.com/design/|8|frontdoor.com|2014-03-19|0|0|0|0|0|0|0|http://www.frontdoor.com/|1|2011-04-05|2014-03-19| | |TextLink|TextLink_Normal|67|62|55|54</Row>
			<Row>http://blog.hgtv.com/design/|8|hgtv&#39;s frontdoor|2014-03-19|0|0|0|0|0|0|0|http://www.frontdoor.com/|1|2011-04-05|2014-03-19| | |TextLink|TextLink_Normal|67|62|55|54</Row>
			<Row>http://blog.hgtv.com/design/|8|frontdoor|2014-03-19|0|0|0|0|0|0|0|http://www.frontdoor.com/?xp=hgtv_footer|1|2012-03-30|2014-03-19| | |TextLink|TextLink_Normal|55|53|55|54</Row>
			<Row>http://blog.hgtv.com/design/|8|curb appeal tricks|2014-03-19|0|0|0|0|0|0|0|http://www.frontdoor.com/curb-appeal?xp=spring|1|2014-03-17|2014-03-19| | |TextLink|TextLink_Normal|53|53|55|54</Row>
			<Row>http://blog.hgtv.com/design/|8|outdoor living spaces of the stars|2014-03-19|0|0|0|0|0|0|0|http://www.frontdoor.com/photos/outdoor-living-spaces-of-the-stars?xp=spring|1|2014-03-17|2014-03-19| | |TextLink|TextLink_Normal|53|53|55|54</Row>
			<Row>http://blog.hgtv.com/design/|8|10 homes with incredible decks|2014-03-19|0|0|0|0|0|0|0|http://www.frontdoor.com/photos/10-homes-for-sale-with-amazing-decks?xp=spring|1|2014-03-17|2014-03-19| | |TextLink|TextLink_Normal|53|53|55|54</Row>
			<Row>http://www.hgtv.com/be-on-hgtv/package/index.html|8|frontdoor.com|2014-03-20|0|0|0|0|0|0|0|http://www.frontdoor.com/|1|2011-11-02|2014-03-20| | |TextLink|TextLink_Normal|67|62|55|54</Row>
			<Row>http://www.hgtv.com/be-on-hgtv/package/index.html|8|hgtv&#39;s frontdoor|2014-03-20|0|0|0|0|0|0|0|http://www.frontdoor.com/|1|2011-11-02|2014-03-20| | |TextLink|TextLink_Normal|67|62|55|54</Row>
			<Row>http://www.hgtv.com/be-on-hgtv/package/index.html|8|frontdoor|2014-03-20|0|0|0|0|0|0|0|http://www.frontdoor.com/?xp=hgtv_footer|1|2011-11-02|2014-03-20| | |TextLink|TextLink_Normal|55|53|55|54</Row>
			<Row>http://www.hgtv.com/be-on-hgtv/package/index.html|8|celebrity homes|2014-03-20|0|0|0|0|0|0|0|http://www.frontdoor.com/photos/celebrity-homes-an-inside-look|1|2014-03-03|2014-03-20| | |TextLink|TextLink_Normal|54|53|55|54</Row>
			<Row>http://www.hgtv.com/be-on-hgtv/package/index.html|8|curb appeal tricks|2014-03-20|0|0|0|0|0|0|0|http://www.frontdoor.com/curb-appeal?xp=spring|1|2014-03-17|2014-03-20| | |TextLink|TextLink_Normal|53|53|55|54</Row>
			<Row>http://www.hgtv.com/be-on-hgtv/package/index.html|8|outdoor living spaces of the stars|2014-03-20|0|0|0|0|0|0|0|http://www.frontdoor.com/photos/outdoor-living-spaces-of-the-stars?xp=spring|1|2014-03-17|2014-03-20| | |TextLink|TextLink_Normal|53|53|55|54</Row>
			<Row>http://www.hgtv.com/be-on-hgtv/package/index.html|8|10 homes with incredible decks|2014-03-20|0|0|0|0|0|0|0|http://www.frontdoor.com/photos/10-homes-for-sale-with-amazing-decks?xp=spring|1|2014-03-17|2014-03-20| | |TextLink|TextLink_Normal|53|53|55|54</Row>
			<Row>http://www.hgtv.com/contact-us/package/index.html|8|frontdoor.com|2014-03-19|0|0|0|0|0|0|0|http://www.frontdoor.com/|1|2011-02-04|2014-03-19| | |TextLink|TextLink_Normal|67|62|55|54</Row>
			<Row>http://www.hgtv.com/contact-us/package/index.html|8|hgtv&#39;s frontdoor|2014-03-19|0|0|0|0|0|0|0|http://www.frontdoor.com/|1|2011-02-04|2014-03-19| | |TextLink|TextLink_Normal|67|62|55|54</Row>
			<Row>http://www.hgtv.com/contact-us/package/index.html|8|frontdoor|2014-03-19|0|0|0|0|0|0|0|http://www.frontdoor.com/?xp=hgtv_footer|1|2012-03-30|2014-03-19| | |TextLink|TextLink_Normal|55|53|55|54</Row>
			<Row>http://www.hgtv.com/contact-us/package/index.html|8|celebrity homes|2014-03-19|0|0|0|0|0|0|0|http://www.frontdoor.com/photos/celebrity-homes-an-inside-look|1|2014-03-03|2014-03-19| | |TextLink|TextLink_Normal|54|53|55|54</Row>
			<Row>http://www.hgtv.com/contact-us/package/index.html|8|curb appeal tricks|2014-03-19|0|0|0|0|0|0|0|http://www.frontdoor.com/curb-appeal?xp=spring|1|2014-03-17|2014-03-19| | |TextLink|TextLink_Normal|53|53|55|54</Row>
			<Row>http://www.hgtv.com/contact-us/package/index.html|8|outdoor living spaces of the stars|2014-03-19|0|0|0|0|0|0|0|http://www.frontdoor.com/photos/outdoor-living-spaces-of-the-stars?xp=spring|1|2014-03-17|2014-03-19| | |TextLink|TextLink_Normal|53|53|55|54</Row>
			<Row>http://www.hgtv.com/contact-us/package/index.html|8|10 homes with incredible decks|2014-03-19|0|0|0|0|0|0|0|http://www.frontdoor.com/photos/10-homes-for-sale-with-amazing-decks?xp=spring|1|2014-03-17|2014-03-19| | |TextLink|TextLink_Normal|53|53|55|54</Row>
			<Row>http://www.hgtv.com/decorating/index.html|8|frontdoor.com|2014-03-19|0|0|0|0|0|0|0|http://www.frontdoor.com/|1|2011-02-04|2014-03-19| | |TextLink|TextLink_Normal|67|62|55|54</Row>
			<Row>http://www.hgtv.com/decorating/index.html|8|hgtv&#39;s frontdoor|2014-03-19|0|0|0|0|0|0|0|http://www.frontdoor.com/|1|2011-02-04|2014-03-19| | |TextLink|TextLink_Normal|67|62|55|54</Row>
			<Row>http://www.hgtv.com/decorating/index.html|8|frontdoor|2014-03-19|0|0|0|0|0|0|0|http://www.frontdoor.com/?xp=hgtv_footer|1|2010-12-06|2014-03-19| | |TextLink|TextLink_Normal|55|53|55|54</Row>
			<Row>http://www.hgtv.com/decorating/index.html|8|celebrity homes|2014-03-19|0|0|0|0|0|0|0|http://www.frontdoor.com/photos/celebrity-homes-an-inside-look|1|2014-03-03|2014-03-19| | |TextLink|TextLink_Normal|54|53|55|54</Row>
			<Row>http://www.hgtv.com/decorating/index.html|8|curb appeal tricks|2014-03-19|0|0|0|0|0|0|0|http://www.frontdoor.com/curb-appeal?xp=spring|1|2014-03-17|2014-03-19| | |TextLink|TextLink_Normal|53|53|55|54</Row>
			<Row>http://www.hgtv.com/decorating/index.html|8|outdoor living spaces of the stars|2014-03-19|0|0|0|0|0|0|0|http://www.frontdoor.com/photos/outdoor-living-spaces-of-the-stars?xp=spring|1|2014-03-17|2014-03-19| | |TextLink|TextLink_Normal|53|53|55|54</Row>
			<Row>http://www.hgtv.com/decorating/index.html|8|10 homes with incredible decks|2014-03-19|0|0|0|0|0|0|0|http://www.frontdoor.com/photos/10-homes-for-sale-with-amazing-decks?xp=spring|1|2014-03-17|2014-03-19| | |TextLink|TextLink_Normal|53|53|55|54</Row>
			<Row>http://my.hgtv.com/registration/register.esi|8|hgtv&#39;s frontdoor|2014-03-19|0|0|0|0|0|0|0|http://www.frontdoor.com/|1|2011-04-05|2014-03-19| | |TextLink|TextLink_Normal|67|62|55|53</Row>
			<Row>http://my.hgtv.com/registration/register.esi|8|frontdoor.com|2014-03-19|0|0|0|0|0|0|0|http://www.frontdoor.com/|1|2011-04-05|2014-03-19| | |TextLink|TextLink_Normal|67|62|55|53</Row>
			<Row>http://my.hgtv.com/registration/register.esi|8|frontdoor|2014-03-19|0|0|0|0|0|0|0|http://www.frontdoor.com/?xp=hgtv_footer|1|2012-03-30|2014-03-19| | |TextLink|TextLink_Normal|55|53|55|53</Row>
			<Row>http://my.hgtv.com/registration/register.esi|8|celebrity homes|2014-03-19|0|0|0|0|0|0|0|http://www.frontdoor.com/photos/celebrity-homes-an-inside-look|1|2014-03-03|2014-03-19| | |TextLink|TextLink_Normal|54|53|55|53</Row>
			<Row>http://my.hgtv.com/registration/register.esi|8|curb appeal tricks|2014-03-19|0|0|0|0|0|0|0|http://www.frontdoor.com/curb-appeal?xp=spring|1|2014-03-17|2014-03-19| | |TextLink|TextLink_Normal|53|53|55|53</Row>
			<Row>http://my.hgtv.com/registration/register.esi|8|outdoor living spaces of the stars|2014-03-19|0|0|0|0|0|0|0|http://www.frontdoor.com/photos/outdoor-living-spaces-of-the-stars?xp=spring|1|2014-03-17|2014-03-19| | |TextLink|TextLink_Normal|53|53|55|53</Row>
			<Row>http://my.hgtv.com/registration/register.esi|8|10 homes with incredible decks|2014-03-19|0|0|0|0|0|0|0|http://www.frontdoor.com/photos/10-homes-for-sale-with-amazing-decks?xp=spring|1|2014-03-17|2014-03-19| | |TextLink|TextLink_Normal|53|53|55|53</Row>
			<Row>http://www.hgtv.com/landscaping/index.html|8|frontdoor.com|2014-03-19|0|0|0|0|0|0|0|http://www.frontdoor.com/|1|2011-02-04|2014-03-19| | |TextLink|TextLink_Normal|67|62|55|53</Row>
			<Row>http://www.hgtv.com/landscaping/index.html|8|hgtv&#39;s frontdoor|2014-03-19|0|0|0|0|0|0|0|http://www.frontdoor.com/|1|2011-02-04|2014-03-19| | |TextLink|TextLink_Normal|67|62|55|53</Row>
			<Row>http://www.hgtv.com/landscaping/index.html|8|frontdoor|2014-03-19|0|0|0|0|0|0|0|http://www.frontdoor.com/?xp=hgtv_footer|1|2011-08-03|2014-03-19| | |TextLink|TextLink_Normal|55|53|55|53</Row>
			<Row>http://www.hgtv.com/landscaping/index.html|8|celebrity homes|2014-03-19|0|0|0|0|0|0|0|http://www.frontdoor.com/photos/celebrity-homes-an-inside-look|1|2014-03-03|2014-03-19| | |TextLink|TextLink_Normal|54|53|55|53</Row>
			<Row>http://www.hgtv.com/landscaping/index.html|8|curb appeal tricks|2014-03-19|0|0|0|0|0|0|0|http://www.frontdoor.com/curb-appeal?xp=spring|1|2014-03-17|2014-03-19| | |TextLink|TextLink_Normal|53|53|55|53</Row>
			<Row>http://www.hgtv.com/landscaping/index.html|8|outdoor living spaces of the stars|2014-03-19|0|0|0|0|0|0|0|http://www.frontdoor.com/photos/outdoor-living-spaces-of-the-stars?xp=spring|1|2014-03-17|2014-03-19| | |TextLink|TextLink_Normal|53|53|55|53</Row>
			<Row>http://www.hgtv.com/landscaping/index.html|8|10 homes with incredible decks|2014-03-19|0|0|0|0|0|0|0|http://www.frontdoor.com/photos/10-homes-for-sale-with-amazing-decks?xp=spring|1|2014-03-17|2014-03-19| | |TextLink|TextLink_Normal|53|53|55|53</Row>
			<Row>http://www.hgtv.com/landscaping/index.html|8|peek inside the extravagant homes of your favorite celebrities!|2014-03-19|0|0|0|0|0|0|0|http://www.frontdoor.com/celebrity-homes?xp=celeb|1|2014-02-24|2014-03-19| | |TextLink|TextLink_Normal|42|40|55|53</Row>
			<Row>http://www.hgtv.com/landscaping/index.html|8|peek inside the extravagant homes of your favorite celebrities!|2014-03-19|0|0|0|1|0|0|0|http://www.frontdoor.com/celebrity-homes?xp=celeb|1|2014-02-24|2014-03-19| | |ImageLink|ImageLink_Normal|42|40|55|53</Row>
			<Row>http://www.hgtv.com/on-tv/index.html|8|frontdoor.com|2014-03-19|0|0|0|0|0|0|0|http://www.frontdoor.com/|1|2011-02-04|2014-03-19| | |TextLink|TextLink_Normal|67|62|55|53</Row>
			<Row>http://www.hgtv.com/on-tv/index.html|8|hgtv&#39;s frontdoor|2014-03-19|0|0|0|0|0|0|0|http://www.frontdoor.com/|1|2011-02-04|2014-03-19| | |TextLink|TextLink_Normal|67|62|55|53</Row>
			<Row>http://www.hgtv.com/on-tv/index.html|8|frontdoor|2014-03-19|0|0|0|0|0|0|0|http://www.frontdoor.com/?xp=hgtv_footer|1|2011-08-03|2014-03-19| | |TextLink|TextLink_Normal|55|53|55|53</Row>
			<Row>http://www.hgtv.com/on-tv/index.html|8|celebrity homes|2014-03-19|0|0|0|0|0|0|0|http://www.frontdoor.com/photos/celebrity-homes-an-inside-look|1|2014-03-03|2014-03-19| | |TextLink|TextLink_Normal|54|53|55|53</Row>
			<Row>http://www.hgtv.com/on-tv/index.html|8|curb appeal tricks|2014-03-19|0|0|0|0|0|0|0|http://www.frontdoor.com/curb-appeal?xp=spring|1|2014-03-17|2014-03-19| | |TextLink|TextLink_Normal|53|53|55|53</Row>
			<Row>http://www.hgtv.com/on-tv/index.html|8|outdoor living spaces of the stars|2014-03-19|0|0|0|0|0|0|0|http://www.frontdoor.com/photos/outdoor-living-spaces-of-the-stars?xp=spring|1|2014-03-17|2014-03-19| | |TextLink|TextLink_Normal|53|53|55|53</Row>
			<Row>http://www.hgtv.com/on-tv/index.html|8|10 homes with incredible decks|2014-03-19|0|0|0|0|0|0|0|http://www.frontdoor.com/photos/10-homes-for-sale-with-amazing-decks?xp=spring|1|2014-03-17|2014-03-19| | |TextLink|TextLink_Normal|53|53|55|53</Row>
			<Row>http://www.hgtv.com/video-library/index.html|8|hgtv&#39;s frontdoor|2014-03-19|0|0|0|0|0|0|0|http://www.frontdoor.com/|1|2011-03-06|2014-03-19| | |TextLink|TextLink_Normal|67|62|55|53</Row>
			<Row>http://www.hgtv.com/video-library/index.html|8|frontdoor.com|2014-03-19|0|0|0|0|0|0|0|http://www.frontdoor.com/|1|2011-03-06|2014-03-19| | |TextLink|TextLink_Normal|67|62|55|53</Row>
			<Row>http://www.hgtv.com/video-library/index.html|8|frontdoor|2014-03-19|0|0|0|0|0|0|0|http://www.frontdoor.com/?xp=hgtv_footer|1|2011-08-03|2014-03-19| | |TextLink|TextLink_Normal|55|53|55|53</Row>
			<Row>http://www.hgtv.com/video-library/index.html|8|celebrity homes|2014-03-19|0|0|0|0|0|0|0|http://www.frontdoor.com/photos/celebrity-homes-an-inside-look|1|2014-03-03|2014-03-19| | |TextLink|TextLink_Normal|54|53|55|53</Row>
			<Row>http://www.hgtv.com/video-library/index.html|8|curb appeal tricks|2014-03-19|0|0|0|0|0|0|0|http://www.frontdoor.com/curb-appeal?xp=spring|1|2014-03-17|2014-03-19| | |TextLink|TextLink_Normal|53|53|55|53</Row>
			<Row>http://www.hgtv.com/video-library/index.html|8|outdoor living spaces of the stars|2014-03-19|0|0|0|0|0|0|0|http://www.frontdoor.com/photos/outdoor-living-spaces-of-the-stars?xp=spring|1|2014-03-17|2014-03-19| | |TextLink|TextLink_Normal|53|53|55|53</Row>
			<Row>http://www.hgtv.com/video-library/index.html|8|10 homes with incredible decks|2014-03-19|0|0|0|0|0|0|0|http://www.frontdoor.com/photos/10-homes-for-sale-with-amazing-decks?xp=spring|1|2014-03-17|2014-03-19| | |TextLink|TextLink_Normal|53|53|55|53</Row>
			<Row>http://www.hgtv.com/rooms/index.html|8|frontdoor.com|2014-03-19|0|0|0|0|0|0|0|http://www.frontdoor.com/|1|2011-05-05|2014-03-19| | |TextLink|TextLink_Normal|67|62|55|53</Row>
			<Row>http://www.hgtv.com/rooms/index.html|8|hgtv&#39;s frontdoor|2014-03-19|0|0|0|0|0|0|0|http://www.frontdoor.com/|1|2011-05-05|2014-03-19| | |TextLink|TextLink_Normal|67|62|55|53</Row>
			<Row>http://www.hgtv.com/rooms/index.html|8|frontdoor|2014-03-19|0|0|0|0|0|0|0|http://www.frontdoor.com/?xp=hgtv_footer|1|2012-03-30|2014-03-19| | |TextLink|TextLink_Normal|55|53|55|53</Row>
			<Row>http://www.hgtv.com/rooms/index.html|8|celebrity homes|2014-03-19|0|0|0|0|0|0|0|http://www.frontdoor.com/photos/celebrity-homes-an-inside-look|1|2014-03-03|2014-03-19| | |TextLink|TextLink_Normal|54|53|55|53</Row>
			<Row>http://www.hgtv.com/rooms/index.html|8|curb appeal tricks|2014-03-19|0|0|0|0|0|0|0|http://www.frontdoor.com/curb-appeal?xp=spring|1|2014-03-17|2014-03-19| | |TextLink|TextLink_Normal|53|53|55|53</Row>
			<Row>http://www.hgtv.com/rooms/index.html|8|outdoor living spaces of the stars|2014-03-19|0|0|0|0|0|0|0|http://www.frontdoor.com/photos/outdoor-living-spaces-of-the-stars?xp=spring|1|2014-03-17|2014-03-19| | |TextLink|TextLink_Normal|53|53|55|53</Row>
			<Row>http://www.hgtv.com/rooms/index.html|8|10 homes with incredible decks|2014-03-19|0|0|0|0|0|0|0|http://www.frontdoor.com/photos/10-homes-for-sale-with-amazing-decks?xp=spring|1|2014-03-17|2014-03-19| | |TextLink|TextLink_Normal|53|53|55|53</Row>
			<Row>http://www.hgtv.com/kitchens/index.html|8|frontdoor.com|2014-03-20|0|0|0|0|0|0|0|http://www.frontdoor.com/|1|2011-02-05|2014-03-20| | |TextLink|TextLink_Normal|67|62|55|53</Row>
			<Row>http://www.hgtv.com/kitchens/index.html|8|hgtv&#39;s frontdoor|2014-03-20|0|0|0|0|0|0|0|http://www.frontdoor.com/|1|2011-02-05|2014-03-20| | |TextLink|TextLink_Normal|67|62|55|53</Row>
			<Row>http://www.hgtv.com/kitchens/index.html|8|frontdoor|2014-03-20|0|0|0|0|0|0|0|http://www.frontdoor.com/?xp=hgtv_footer|1|2011-04-06|2014-03-20| | |TextLink|TextLink_Normal|55|53|55|53</Row>
			<Row>http://www.hgtv.com/kitchens/index.html|8|celebrity homes|2014-03-20|0|0|0|0|0|0|0|http://www.frontdoor.com/photos/celebrity-homes-an-inside-look|1|2014-03-03|2014-03-20| | |TextLink|TextLink_Normal|54|53|55|53</Row>
			<Row>http://www.hgtv.com/kitchens/index.html|8|curb appeal tricks|2014-03-20|0|0|0|0|0|0|0|http://www.frontdoor.com/curb-appeal?xp=spring|1|2014-03-17|2014-03-20| | |TextLink|TextLink_Normal|53|53|55|53</Row>
			<Row>http://www.hgtv.com/kitchens/index.html|8|outdoor living spaces of the stars|2014-03-20|0|0|0|0|0|0|0|http://www.frontdoor.com/photos/outdoor-living-spaces-of-the-stars?xp=spring|1|2014-03-17|2014-03-20| | |TextLink|TextLink_Normal|53|53|55|53</Row>
			<Row>http://www.hgtv.com/kitchens/index.html|8|10 homes with incredible decks|2014-03-20|0|0|0|0|0|0|0|http://www.frontdoor.com/photos/10-homes-for-sale-with-amazing-decks?xp=spring|1|2014-03-17|2014-03-20| | |TextLink|TextLink_Normal|53|53|55|53</Row>
			<Row>http://www.hgtv.com/kitchens/index.html|8|peek inside the extravagant homes of your favorite celebrities!|2014-03-20|0|0|0|0|0|0|0|http://www.frontdoor.com/celebrity-homes?xp=celeb|1|2014-02-24|2014-03-20| | |TextLink|TextLink_Normal|42|40|55|53</Row>
			<Row>http://www.hgtv.com/kitchens/index.html|8|peek inside the extravagant homes of your favorite celebrities!|2014-03-20|0|0|0|1|0|0|0|http://www.frontdoor.com/celebrity-homes?xp=celeb|1|2014-02-24|2014-03-20| | |ImageLink|ImageLink_Normal|42|40|55|53</Row>
			<Row>http://www.hgtv.com/smart-home/index.html|8|hgtv&#39;s frontdoor|2014-03-20|0|0|0|0|0|0|0|http://www.frontdoor.com/|1|2013-07-24|2014-03-20| | |TextLink|TextLink_Normal|67|62|55|53</Row>
			<Row>http://www.hgtv.com/smart-home/index.html|8|frontdoor.com|2014-03-20|0|0|0|0|0|0|0|http://www.frontdoor.com/|1|2013-07-24|2014-03-20| | |TextLink|TextLink_Normal|67|62|55|53</Row>
			<Row>http://www.hgtv.com/smart-home/index.html|8|frontdoor|2014-03-20|0|0|0|0|0|0|0|http://www.frontdoor.com/?xp=hgtv_footer|1|2013-02-24|2014-03-20| | |TextLink|TextLink_Normal|55|53|55|53</Row>
			<Row>http://www.hgtv.com/smart-home/index.html|8|celebrity homes|2014-03-20|0|0|0|0|0|0|0|http://www.frontdoor.com/photos/celebrity-homes-an-inside-look|1|2014-03-03|2014-03-20| | |TextLink|TextLink_Normal|54|53|55|53</Row>
			<Row>http://www.hgtv.com/smart-home/index.html|8|curb appeal tricks|2014-03-20|0|0|0|0|0|0|0|http://www.frontdoor.com/curb-appeal?xp=spring|1|2014-03-17|2014-03-20| | |TextLink|TextLink_Normal|53|53|55|53</Row>
			<Row>http://www.hgtv.com/smart-home/index.html|8|outdoor living spaces of the stars|2014-03-20|0|0|0|0|0|0|0|http://www.frontdoor.com/photos/outdoor-living-spaces-of-the-stars?xp=spring|1|2014-03-17|2014-03-20| | |TextLink|TextLink_Normal|53|53|55|53</Row>
			<Row>http://www.hgtv.com/smart-home/index.html|8|10 homes with incredible decks|2014-03-20|0|0|0|0|0|0|0|http://www.frontdoor.com/photos/10-homes-for-sale-with-amazing-decks?xp=spring|1|2014-03-17|2014-03-20| | |TextLink|TextLink_Normal|53|53|55|53</Row>
			<Row>http://www.hgtv.com/smart-home/index.html|8|profile: nashville|2014-03-20|0|0|0|0|0|0|0|http://www.frontdoor.com/places/profile-nashville-tennessee|1|2014-03-13|2014-03-20| | |TextLink|TextLink_Normal|31|33|55|53</Row>
			<Row>http://www.hgtv.com/photos/index.html|8|frontdoor.com|2014-03-19|0|0|0|0|0|0|0|http://www.frontdoor.com/|1|2013-08-22|2014-03-19| | |TextLink|TextLink_Normal|67|62|55|53</Row>
			<Row>http://www.hgtv.com/photos/index.html|8|hgtv&#39;s frontdoor|2014-03-19|0|0|0|0|0|0|0|http://www.frontdoor.com/|1|2013-08-22|2014-03-19| | |TextLink|TextLink_Normal|67|62|55|53</Row>
			<Row>http://www.hgtv.com/photos/index.html|8|frontdoor|2014-03-19|0|0|0|0|0|0|0|http://www.frontdoor.com/?xp=hgtv_footer|1|2013-02-23|2014-03-19| | |TextLink|TextLink_Normal|55|53|55|53</Row>
			<Row>http://www.hgtv.com/photos/index.html|8|celebrity homes|2014-03-19|0|0|0|0|0|0|0|http://www.frontdoor.com/photos/celebrity-homes-an-inside-look|1|2014-03-03|2014-03-19| | |TextLink|TextLink_Normal|54|53|55|53</Row>
			<Row>http://www.hgtv.com/photos/index.html|8|curb appeal tricks|2014-03-19|0|0|0|0|0|0|0|http://www.frontdoor.com/curb-appeal?xp=spring|1|2014-03-17|2014-03-19| | |TextLink|TextLink_Normal|53|53|55|53</Row>
			<Row>http://www.hgtv.com/photos/index.html|8|outdoor living spaces of the stars|2014-03-19|0|0|0|0|0|0|0|http://www.frontdoor.com/photos/outdoor-living-spaces-of-the-stars?xp=spring|1|2014-03-17|2014-03-19| | |TextLink|TextLink_Normal|53|53|55|53</Row>
			<Row>http://www.hgtv.com/photos/index.html|8|10 homes with incredible decks|2014-03-19|0|0|0|0|0|0|0|http://www.frontdoor.com/photos/10-homes-for-sale-with-amazing-decks?xp=spring|1|2014-03-17|2014-03-19| | |TextLink|TextLink_Normal|53|53|55|53</Row>
			<Row>http://www.hgtv.com/about-us/questions-for-hgtvcom/index.html|8|hgtv&#39;s frontdoor|2014-03-19|0|0|0|0|0|0|0|http://www.frontdoor.com/|1|2011-02-04|2014-03-19| | |TextLink|TextLink_Normal|67|62|55|53</Row>
			<Row>http://www.hgtv.com/about-us/questions-for-hgtvcom/index.html|8|frontdoor.com|2014-03-19|0|0|0|0|0|0|0|http://www.frontdoor.com/|1|2011-02-04|2014-03-19| | |TextLink|TextLink_Normal|67|62|55|53</Row>
			<Row>http://www.hgtv.com/about-us/questions-for-hgtvcom/index.html|8|frontdoor|2014-03-19|0|0|0|0|0|0|0|http://www.frontdoor.com/?xp=hgtv_footer|1|2011-08-03|2014-03-19| | |TextLink|TextLink_Normal|55|53|55|53</Row>
			<Row>http://www.hgtv.com/about-us/questions-for-hgtvcom/index.html|8|celebrity homes|2014-03-19|0|0|0|0|0|0|0|http://www.frontdoor.com/photos/celebrity-homes-an-inside-look|1|2014-03-03|2014-03-19| | |TextLink|TextLink_Normal|54|53|55|53</Row>
			<Row>http://www.hgtv.com/about-us/questions-for-hgtvcom/index.html|8|curb appeal tricks|2014-03-19|0|0|0|0|0|0|0|http://www.frontdoor.com/curb-appeal?xp=spring|1|2014-03-17|2014-03-19| | |TextLink|TextLink_Normal|53|53|55|53</Row>
			<Row>http://www.hgtv.com/about-us/questions-for-hgtvcom/index.html|8|outdoor living spaces of the stars|2014-03-19|0|0|0|0|0|0|0|http://www.frontdoor.com/photos/outdoor-living-spaces-of-the-stars?xp=spring|1|2014-03-17|2014-03-19| | |TextLink|TextLink_Normal|53|53|55|53</Row>
			<Row>http://www.hgtv.com/about-us/questions-for-hgtvcom/index.html|8|10 homes with incredible decks|2014-03-19|0|0|0|0|0|0|0|http://www.frontdoor.com/photos/10-homes-for-sale-with-amazing-decks?xp=spring|1|2014-03-17|2014-03-19| | |TextLink|TextLink_Normal|53|53|55|53</Row>
			<Row>http://www.hgtv.com/handmade/index.html|8|hgtv&#39;s frontdoor|2014-03-19|0|0|0|0|0|0|0|http://www.frontdoor.com/|1|2011-12-01|2014-03-19| | |TextLink|TextLink_Normal|67|62|55|53</Row>
			<Row>http://www.hgtv.com/handmade/index.html|8|frontdoor.com|2014-03-19|0|0|0|0|0|0|0|http://www.frontdoor.com/|1|2011-12-01|2014-03-19| | |TextLink|TextLink_Normal|67|62|55|53</Row>
			<Row>http://www.hgtv.com/handmade/index.html|8|frontdoor|2014-03-19|0|0|0|0|0|0|0|http://www.frontdoor.com/?xp=hgtv_footer|1|2012-03-30|2014-03-19| | |TextLink|TextLink_Normal|55|53|55|53</Row>
			<Row>http://www.hgtv.com/handmade/index.html|8|celebrity homes|2014-03-19|0|0|0|0|0|0|0|http://www.frontdoor.com/photos/celebrity-homes-an-inside-look|1|2014-03-03|2014-03-19| | |TextLink|TextLink_Normal|54|53|55|53</Row>
			<Row>http://www.hgtv.com/handmade/index.html|8|curb appeal tricks|2014-03-19|0|0|0|0|0|0|0|http://www.frontdoor.com/curb-appeal?xp=spring|1|2014-03-17|2014-03-19| | |TextLink|TextLink_Normal|53|53|55|53</Row>
			<Row>http://www.hgtv.com/handmade/index.html|8|outdoor living spaces of the stars|2014-03-19|0|0|0|0|0|0|0|http://www.frontdoor.com/photos/outdoor-living-spaces-of-the-stars?xp=spring|1|2014-03-17|2014-03-19| | |TextLink|TextLink_Normal|53|53|55|53</Row>
			<Row>http://www.hgtv.com/handmade/index.html|8|10 homes with incredible decks|2014-03-19|0|0|0|0|0|0|0|http://www.frontdoor.com/photos/10-homes-for-sale-with-amazing-decks?xp=spring|1|2014-03-17|2014-03-19| | |TextLink|TextLink_Normal|53|53|55|53</Row>
			<Row>http://www.hgtv.com/handmade/index.html|8|peek inside the extravagant homes of your favorite celebrities!|2014-03-19|0|0|0|1|0|0|0|http://www.frontdoor.com/celebrity-homes?xp=celeb|1|2014-02-24|2014-03-19| | |ImageLink|ImageLink_Normal|42|40|55|53</Row>
			<Row>http://www.hgtv.com/handmade/index.html|8|peek inside the extravagant homes of your favorite celebrities!|2014-03-19|0|0|0|0|0|0|0|http://www.frontdoor.com/celebrity-homes?xp=celeb|1|2014-02-24|2014-03-19| | |TextLink|TextLink_Normal|42|40|55|53</Row>
			<Row>http://www.hgtv.com/hgtv/about_us/index/0,,HGTV_32664_490_-1,00.html?a=b|8|frontdoor.com|2014-03-19|0|0|0|0|0|0|0|http://www.frontdoor.com/|1|2012-08-27|2014-03-19| | |TextLink|TextLink_Normal|67|62|55|53</Row>
			<Row>http://www.hgtv.com/hgtv/about_us/index/0,,HGTV_32664_490_-1,00.html?a=b|8|hgtv&#39;s frontdoor|2014-03-19|0|0|0|0|0|0|0|http://www.frontdoor.com/|1|2012-08-27|2014-03-19| | |TextLink|TextLink_Normal|67|62|55|53</Row>
			<Row>http://www.hgtv.com/hgtv/about_us/index/0,,HGTV_32664_490_-1,00.html?a=b|8|frontdoor|2014-03-19|0|0|0|0|0|0|0|http://www.frontdoor.com/?xp=hgtv_footer|1|2012-08-27|2014-03-19| | |TextLink|TextLink_Normal|55|53|55|53</Row>
			<Row>http://www.hgtv.com/hgtv/about_us/index/0,,HGTV_32664_490_-1,00.html?a=b|8|celebrity homes|2014-03-19|0|0|0|0|0|0|0|http://www.frontdoor.com/photos/celebrity-homes-an-inside-look|1|2014-03-03|2014-03-19| | |TextLink|TextLink_Normal|54|53|55|53</Row>
			<Row>http://www.hgtv.com/hgtv/about_us/index/0,,HGTV_32664_490_-1,00.html?a=b|8|curb appeal tricks|2014-03-19|0|0|0|0|0|0|0|http://www.frontdoor.com/curb-appeal?xp=spring|1|2014-03-17|2014-03-19| | |TextLink|TextLink_Normal|53|53|55|53</Row>
			<Row>http://www.hgtv.com/hgtv/about_us/index/0,,HGTV_32664_490_-1,00.html?a=b|8|outdoor living spaces of the stars|2014-03-19|0|0|0|0|0|0|0|http://www.frontdoor.com/photos/outdoor-living-spaces-of-the-stars?xp=spring|1|2014-03-17|2014-03-19| | |TextLink|TextLink_Normal|53|53|55|53</Row>
			<Row>http://www.hgtv.com/hgtv/about_us/index/0,,HGTV_32664_490_-1,00.html?a=b|8|10 homes with incredible decks|2014-03-19|0|0|0|0|0|0|0|http://www.frontdoor.com/photos/10-homes-for-sale-with-amazing-decks?xp=spring|1|2014-03-17|2014-03-19| | |TextLink|TextLink_Normal|53|53|55|53</Row>
			<Row>http://my.hgtv.com/registration/login.esi|8|hgtv&#39;s frontdoor|2014-03-19|0|0|0|0|0|0|0|http://www.frontdoor.com/|1|2011-05-05|2014-03-19| | |TextLink|TextLink_Normal|67|62|55|53</Row>
			<Row>http://my.hgtv.com/registration/login.esi|8|frontdoor.com|2014-03-19|0|0|0|0|0|0|0|http://www.frontdoor.com/|1|2011-05-05|2014-03-19| | |TextLink|TextLink_Normal|67|62|55|53</Row>
			<Row>http://my.hgtv.com/registration/login.esi|8|frontdoor|2014-03-19|0|0|0|0|0|0|0|http://www.frontdoor.com/?xp=hgtv_footer|1|2011-03-06|2014-03-19| | |TextLink|TextLink_Normal|55|53|55|53</Row>
			<Row>http://my.hgtv.com/registration/login.esi|8|celebrity homes|2014-03-19|0|0|0|0|0|0|0|http://www.frontdoor.com/photos/celebrity-homes-an-inside-look|1|2014-03-03|2014-03-19| | |TextLink|TextLink_Normal|54|53|55|53</Row>
			<Row>http://my.hgtv.com/registration/login.esi|8|curb appeal tricks|2014-03-19|0|0|0|0|0|0|0|http://www.frontdoor.com/curb-appeal?xp=spring|1|2014-03-17|2014-03-19| | |TextLink|TextLink_Normal|53|53|55|53</Row>
			<Row>http://my.hgtv.com/registration/login.esi|8|outdoor living spaces of the stars|2014-03-19|0|0|0|0|0|0|0|http://www.frontdoor.com/photos/outdoor-living-spaces-of-the-stars?xp=spring|1|2014-03-17|2014-03-19| | |TextLink|TextLink_Normal|53|53|55|53</Row>
			<Row>http://my.hgtv.com/registration/login.esi|8|10 homes with incredible decks|2014-03-19|0|0|0|0|0|0|0|http://www.frontdoor.com/photos/10-homes-for-sale-with-amazing-decks?xp=spring|1|2014-03-17|2014-03-19| | |TextLink|TextLink_Normal|53|53|55|53</Row>
			<Row>http://boards.hgtv.com/eve/|8|frontdoor.com|2014-03-19|0|0|0|0|0|0|0|http://www.frontdoor.com/|1|2012-05-29|2014-03-19| | |TextLink|TextLink_Normal|67|62|55|53</Row>
			<Row>http://boards.hgtv.com/eve/|8|hgtv&#39;s frontdoor|2014-03-19|0|0|0|0|0|0|0|http://www.frontdoor.com/|1|2012-05-29|2014-03-19| | |TextLink|TextLink_Normal|67|62|55|53</Row>
			<Row>http://boards.hgtv.com/eve/|8|frontdoor|2014-03-19|0|0|0|0|0|0|0|http://www.frontdoor.com/?xp=hgtv_footer|1|2012-05-29|2014-03-19| | |TextLink|TextLink_Normal|55|53|55|53</Row>
			<Row>http://boards.hgtv.com/eve/|8|tour famous real estate|2014-03-19|0|0|0|0|0|0|0|http://www.frontdoor.com/buy/celebrity-homes/56254?xp=hgtv_footer|1|2012-05-29|2014-03-19| | |TextLink|TextLink_Normal|31|31|55|53</Row>
			<Row>http://boards.hgtv.com/eve/|8|the ultimate house hunt|2014-03-19|0|0|0|0|0|0|0|http://www.frontdoor.com/buy/the-doory-awards/56347?xp=hgtv_footer|1|2012-05-29|2014-03-19| | |TextLink|TextLink_Normal|31|31|55|53</Row>
			<Row>http://boards.hgtv.com/eve/|8|budget curb appeal|2014-03-19|0|0|0|0|0|0|0|http://www.frontdoor.com/sell/8-budget-curb-appeal-projects/pictures/pg275?xp=hgtv_footer|1|2012-05-29|2014-03-19| | |TextLink|TextLink_Normal|31|31|55|53</Row>
			<Row>http://www.hgtv.com/dream-home/index.html|8|frontdoor.com|2014-03-20|0|0|0|0|0|0|0|http://www.frontdoor.com/|1|2011-02-05|2014-03-20| | |TextLink|TextLink_Normal|67|62|55|53</Row>
			<Row>http://www.hgtv.com/dream-home/index.html|8|hgtv&#39;s frontdoor|2014-03-20|0|0|0|0|0|0|0|http://www.frontdoor.com/|1|2011-02-05|2014-03-20| | |TextLink|TextLink_Normal|67|62|55|53</Row>
			<Row>http://www.hgtv.com/dream-home/index.html|8|frontdoor|2014-03-20|0|0|0|0|0|0|0|http://www.frontdoor.com/?xp=hgtv_footer|1|2011-11-02|2014-03-20| | |TextLink|TextLink_Normal|55|53|55|53</Row>
			<Row>http://www.hgtv.com/dream-home/index.html|8|celebrity homes|2014-03-20|0|0|0|0|0|0|0|http://www.frontdoor.com/photos/celebrity-homes-an-inside-look|1|2014-03-03|2014-03-20| | |TextLink|TextLink_Normal|54|53|55|53</Row>
			<Row>http://www.hgtv.com/dream-home/index.html|8|curb appeal tricks|2014-03-20|0|0|0|0|0|0|0|http://www.frontdoor.com/curb-appeal?xp=spring|1|2014-03-17|2014-03-20| | |TextLink|TextLink_Normal|53|53|55|53</Row>
			<Row>http://www.hgtv.com/dream-home/index.html|8|outdoor living spaces of the stars|2014-03-20|0|0|0|0|0|0|0|http://www.frontdoor.com/photos/outdoor-living-spaces-of-the-stars?xp=spring|1|2014-03-17|2014-03-20| | |TextLink|TextLink_Normal|53|53|55|53</Row>
			<Row>http://www.hgtv.com/dream-home/index.html|8|10 homes with incredible decks|2014-03-20|0|0|0|0|0|0|0|http://www.frontdoor.com/photos/10-homes-for-sale-with-amazing-decks?xp=spring|1|2014-03-17|2014-03-20| | |TextLink|TextLink_Normal|53|53|55|53</Row>
			<Row>http://www.hgtv.com/dream-home/index.html|8|truckee, ca|2014-03-20|0|0|0|0|0|0|0|http://www.frontdoor.com/dreamhome|1|2013-08-23|2014-03-20| | |TextLink|TextLink_Normal|41|38|55|53</Row>
			<Row>http://www.hgtv.com/dream-home/index.html|8|lake tahoe hot spots|2014-03-20|0|0|0|0|0|0|0|http://www.frontdoor.com/photos/lake-tahoe-hot-spots-and-tourist-attractions|1|2013-09-22|2014-03-20| | |TextLink|TextLink_Normal|40|38|55|53</Row>
			<Row>http://www.hgtv.com/dream-home/index.html|8|around the neighborhood|2014-03-20|0|0|0|0|0|0|0|http://www.frontdoor.com/places/5-great-neighborhoods-in-the-lake-tahoe-area|1|2013-12-15|2014-03-20| | |TextLink|TextLink_Normal|39|38|55|53</Row>
			<Row>http://www.hgtv.com/dream-home/index.html|8| |2014-03-20|0|0|0|1|0|0|0|http://www.frontdoor.com/photos/lake-tahoe-adventures|1|2013-08-23|2014-03-20| | |ImageLink|ImageLink_Normal|34|34|55|53</Row>
		</DataTable>
		<DataTable Name="DomainsInfo" RowsCount="13" Headers="DomainID|Domain|AlexaRank|RefDomains|ExtBackLinks|IndexedURLs|CrawledURLs|FirstCrawled|LastSuccessfulCrawl|IP|SubNet|CountryCode|TLD|CitationFlow|TrustFlow">
			<Row>0|food.com|1362|76891|21662673|15372171|1533744|2008-08-20|2014-03-20|23.15.7.137|23.15.7.0|US|com|73|65</Row>
			<Row>1|hgtv.com|3375|149947|117333626|5914958|1573370|2008-08-19|2014-03-20|207.152.124.42|207.152.124.0|US|com|65|70</Row>
			<Row>2|diynetwork.com|6426|84380|109254349|4046146|1126064|2008-08-18|2014-03-20|207.152.124.147|207.152.124.0|US|com|62|67</Row>
			<Row>3|scrippsnetworksinteractive.com|184796|2805|12633744|50021|42907|2008-11-12|2014-03-20|204.78.32.205|204.78.32.0|US|com|53|51</Row>
			<Row>4|travelchannel.com|7956|95041|29719933|2170371|975719|2008-08-18|2014-03-20|65.172.31.17|65.172.31.0|US|com|62|68</Row>
			<Row>5|gactv.com|61570|45371|33809875|448268|219521|2008-08-19|2014-03-20|204.78.50.141|204.78.50.0|US|com|53|52</Row>
			<Row>6|hgtvremodels.com|24715|7569|10966456|229187|106238|2011-10-15|2014-03-20|90.84.59.193|90.84.59.0|FR|com|53|51</Row>
			<Row>7|hgtvgardens.com|54490|2001|5990018|390749|248640|2012-06-21|2014-03-20|23.23.103.115|23.23.103.0|US|com|49|49</Row>
			<Row>8|cookingchanneltv.com|17275|22954|20390294|1528337|298842|2010-06-17|2014-03-20|77.109.171.136|77.109.171.0|CH|com|59|57</Row>
			<Row>9|scrippsnetworksdigital.com|449492|501|2094211|2608|2441|2011-04-10|2014-03-20|74.81.193.61|74.81.193.0|US|com|46|46</Row>
			<Row>10|hgtvhome.com|143834|688|1017322|462|332|2012-11-29|2014-03-20|75.126.74.3|75.126.74.0|US|com|43|45</Row>
			<Row>11|foodnetwork.com|835|234424|72469058|5301786|1025333|2008-08-20|2014-03-20|23.15.7.152|23.15.7.0|US|com|81|76</Row>
			<Row>12|roomzaar.com|74104|8445|7864902|2176822|573542|2009-02-23|2014-03-20|209.8.115.160|209.8.115.0|US|com|44|45</Row>
		</DataTable>
	</DataTables>
</Result>
